azpipeline/__init__.py
azpipeline/config.py
azpipeline/libs/__init__.py
azpipeline/libs/utils.py
azpipeline/models.py
azpipeline/py.typed
azpipeline-0.1.0.dist-info/METADATA
azpipeline-0.1.0.dist-info/WHEEL
azpipeline-0.1.0.dist-info/RECORD
