Metadata-Version: 2.1
Name: azpipeline
Version: 0.1.0
Summary: Interact with azure pipelines using python
Home-page: https://nidhaloff.github.io/azpipeline
License: MIT
Author: Nidhal Baccouri
Author-email: nidhalbacc@gmail.com
Requires-Python: >=3.7.1,<4.0
Classifier: Development Status :: 4 - Beta
Classifier: Intended Audience :: Developers
Classifier: License :: OSI Approved :: MIT License
Classifier: Operating System :: OS Independent
Classifier: Programming Language :: Python
Classifier: Programming Language :: Python :: 3
Classifier: Programming Language :: Python :: 3.8
Classifier: Programming Language :: Python :: 3.9
Classifier: Programming Language :: Python :: 3.10
Classifier: Programming Language :: Python :: 3.11
Classifier: Programming Language :: Python :: 3
Classifier: Programming Language :: Python :: 3.7
Classifier: Programming Language :: Python :: 3.8
Classifier: Programming Language :: Python :: 3.9
Classifier: Topic :: Software Development :: Libraries :: Python Modules
Classifier: Typing :: Typed
Requires-Dist: azure-devops (>=7.1.0b3,<8.0.0)
Project-URL: Documentation, https://nidhaloff.github.io/azpipeline
Project-URL: Repository, https://github.com/nidhaloff/azpipeline
